borders/__init__.py
omim_data_borders-10.3.0rc2.data/data/omim-data/borders.tar.xz
omim_data_borders-10.3.0rc2.data/data/omim-data/packed_polygons.bin
omim_data_borders-10.3.0rc2.dist-info/METADATA
omim_data_borders-10.3.0rc2.dist-info/WHEEL
omim_data_borders-10.3.0rc2.dist-info/top_level.txt
omim_data_borders-10.3.0rc2.dist-info/RECORD
