Metadata-Version: 2.1
Name: omim-data-borders
Version: 10.3.0rc2
Summary: This package contains borders data files.
Home-page: https://github.com/mapsme
Author: My.com B.V. (Mail.Ru Group)
Author-email: dev@maps.me
License: UNKNOWN
Platform: UNKNOWN
Classifier: License :: OSI Approved :: Apache Software License
Classifier: Programming Language :: Python :: 2
Classifier: Programming Language :: Python :: 2.7
Classifier: Programming Language :: Python :: 3
Classifier: Programming Language :: Python :: 3.5
Classifier: Programming Language :: Python :: 3.6
Classifier: Programming Language :: Python :: 3.7
Classifier: Programming Language :: Python :: 3.8
Classifier: Programming Language :: Python :: 3.9
Requires-Dist: omim-data-files (==10.3.0rc2)
